pynamical/__init__.py
pynamical/pynamical.py
pynamical-0.3.3.dist-info/licenses/LICENSE.txt
pynamical-0.3.3.dist-info/METADATA
pynamical-0.3.3.dist-info/WHEEL
pynamical-0.3.3.dist-info/top_level.txt
pynamical-0.3.3.dist-info/RECORD
